.DS_Store
hushigi_grammar/__init__.py
hushigi_grammar/data.json
hushigi_grammar-0.0.6.dist-info/LICENSE.md
hushigi_grammar-0.0.6.dist-info/METADATA
hushigi_grammar-0.0.6.dist-info/WHEEL
hushigi_grammar-0.0.6.dist-info/top_level.txt
hushigi_grammar-0.0.6.dist-info/RECORD
