Metadata-Version: 2.1
Name: hushigi_grammar
Version: 0.0.6
Summary: Assistant for aiding conversational fluency for Japanese language.
Home-page: https://github.com/hushigidea/hushigi-grammar
Download-URL: https://github.com/hushigidea/hushigi-grammar/tarball/0.0.6
Author: Wei Jiang
Author-email: jiangjay818@gmail.com
License: BSD
Classifier: Development Status :: 3 - Alpha
Classifier: Intended Audience :: Developers
Classifier: Programming Language :: Python :: 3
License-File: LICENSE.md
